{
  "combo": "EA",
  "phases": [
    "E",
    "A"
  ],
  "isolated": {
    "E": {
      "mean_ms": 70.709,
      "median_ms": 70.465,
      "std_ms": 0.741,
      "min_ms": 70.103,
      "max_ms": 74.406,
      "p10_ms": 70.248,
      "p90_ms": 71.25,
      "p99_ms": 73.41,
      "cv_pct": 1.05,
      "n": 40,
      "all_ms": [
        70.551,
        70.437,
        70.337,
        70.494,
        70.32,
        71.853,
        70.832,
        70.19,
        70.25,
        70.222,
        70.532,
        70.387,
        71.751,
        70.263,
        70.471,
        70.639,
        70.278,
        71.078,
        71.414,
        70.608,
        74.406,
        70.277,
        70.374,
        70.459,
        70.151,
        71.026,
        70.583,
        70.27,
        70.276,
        70.49,
        70.309,
        70.42,
        70.928,
        70.417,
        70.103,
        70.325,
        71.011,
        71.225,
        71.231,
        71.168
      ]
    },
    "A": {
      "mean_ms": 51.245,
      "median_ms": 51.205,
      "std_ms": 0.166,
      "min_ms": 51.038,
      "max_ms": 51.917,
      "p10_ms": 51.1,
      "p90_ms": 51.425,
      "p99_ms": 51.797,
      "cv_pct": 0.32,
      "n": 40,
      "all_ms": [
        51.224,
        51.067,
        51.917,
        51.178,
        51.285,
        51.151,
        51.207,
        51.256,
        51.227,
        51.2,
        51.248,
        51.419,
        51.143,
        51.294,
        51.147,
        51.206,
        51.204,
        51.142,
        51.07,
        51.282,
        51.337,
        51.152,
        51.038,
        51.122,
        51.104,
        51.229,
        51.185,
        51.459,
        51.193,
        51.421,
        51.125,
        51.508,
        51.188,
        51.126,
        51.057,
        51.175,
        51.341,
        51.331,
        51.24,
        51.609
      ]
    }
  },
  "colocated": {
    "E": {
      "mean_ms": 103.991,
      "median_ms": 68.416,
      "std_ms": 41.796,
      "min_ms": 67.876,
      "max_ms": 158.025,
      "p10_ms": 67.941,
      "p90_ms": 154.703,
      "p99_ms": 157.582,
      "cv_pct": 40.19,
      "n": 40,
      "all_ms": [
        121.75,
        156.89,
        155.897,
        153.698,
        154.522,
        154.66,
        158.025,
        147.132,
        154.89,
        153.605,
        154.383,
        154.407,
        147.104,
        154.682,
        154.067,
        145.979,
        153.52,
        86.455,
        68.674,
        68.14,
        68.043,
        67.972,
        68.226,
        68.149,
        67.899,
        68.198,
        67.942,
        67.876,
        67.928,
        67.984,
        67.962,
        68.606,
        68.086,
        68.013,
        68.04,
        68.155,
        68.136,
        67.909,
        68.007,
        68.026
      ]
    },
    "A": {
      "mean_ms": 64.597,
      "median_ms": 62.767,
      "std_ms": 9.499,
      "min_ms": 58.467,
      "max_ms": 120.935,
      "p10_ms": 60.257,
      "p90_ms": 66.793,
      "p99_ms": 101.536,
      "cv_pct": 14.71,
      "n": 40,
      "all_ms": [
        120.935,
        71.194,
        63.497,
        60.504,
        65.277,
        60.838,
        63.327,
        61.939,
        62.33,
        64.25,
        60.008,
        61.75,
        61.915,
        64.058,
        66.449,
        60.107,
        62.863,
        62.295,
        64.488,
        64.87,
        58.467,
        66.172,
        62.02,
        65.646,
        63.577,
        62.479,
        68.788,
        60.274,
        66.947,
        62.379,
        62.815,
        63.573,
        58.673,
        62.763,
        62.322,
        62.046,
        62.77,
        62.107,
        66.776,
        60.375
      ]
    }
  },
  "inflation": {
    "E": 0.971,
    "A": 1.226
  },
  "gpu": 0,
  "warmup": 15,
  "iterations": 40,
  "action_k": 10,
  "use_cuda": true
}