{
  "combo": "PD",
  "phases": [
    "P",
    "D"
  ],
  "isolated": {
    "P": {
      "mean_ms": 30.012,
      "median_ms": 29.98,
      "std_ms": 0.162,
      "min_ms": 29.685,
      "max_ms": 30.562,
      "p10_ms": 29.891,
      "p90_ms": 30.16,
      "p99_ms": 30.555,
      "cv_pct": 0.54,
      "n": 40,
      "all_ms": [
        29.919,
        30.07,
        30.002,
        29.966,
        29.939,
        29.989,
        30.072,
        30.05,
        30.074,
        29.976,
        29.95,
        29.921,
        29.979,
        30.076,
        29.901,
        29.894,
        29.915,
        29.685,
        29.779,
        30.544,
        30.562,
        29.975,
        30.042,
        30.104,
        30.023,
        30.037,
        30.155,
        29.999,
        29.915,
        29.915,
        30.006,
        29.865,
        29.917,
        29.946,
        29.871,
        30.078,
        29.967,
        29.981,
        30.23,
        30.209
      ]
    },
    "D": {
      "mean_ms": 23.955,
      "median_ms": 23.942,
      "std_ms": 0.191,
      "min_ms": 23.653,
      "max_ms": 24.652,
      "p10_ms": 23.761,
      "p90_ms": 24.134,
      "p99_ms": 24.601,
      "cv_pct": 0.8,
      "n": 40,
      "all_ms": [
        23.851,
        23.834,
        23.826,
        23.836,
        23.755,
        24.006,
        24.163,
        24.523,
        24.21,
        24.064,
        23.869,
        23.898,
        23.991,
        23.821,
        23.964,
        23.931,
        23.653,
        23.762,
        23.851,
        23.676,
        23.853,
        23.853,
        23.745,
        23.999,
        23.809,
        23.952,
        23.945,
        24.131,
        24.088,
        24.032,
        23.998,
        24.652,
        23.969,
        24.011,
        23.898,
        23.922,
        23.974,
        23.938,
        23.985,
        23.948
      ]
    }
  },
  "colocated": {
    "P": {
      "mean_ms": 65.376,
      "median_ms": 72.395,
      "std_ms": 16.499,
      "min_ms": 28.748,
      "max_ms": 76.405,
      "p10_ms": 29.19,
      "p90_ms": 76.067,
      "p99_ms": 76.313,
      "cv_pct": 25.24,
      "n": 40,
      "all_ms": [
        63.077,
        66.326,
        64.837,
        69.652,
        71.186,
        72.342,
        72.081,
        72.449,
        72.009,
        71.188,
        71.336,
        73.295,
        72.771,
        72.027,
        71.182,
        73.056,
        72.929,
        75.271,
        73.83,
        75.897,
        76.125,
        76.405,
        75.488,
        75.066,
        76.061,
        76.169,
        75.125,
        74.849,
        74.811,
        75.171,
        76.166,
        75.544,
        65.831,
        38.415,
        32.48,
        29.217,
        28.869,
        28.951,
        28.795,
        28.748
      ]
    },
    "D": {
      "mean_ms": 59.615,
      "median_ms": 59.276,
      "std_ms": 2.341,
      "min_ms": 57.425,
      "max_ms": 73.086,
      "p10_ms": 58.33,
      "p90_ms": 60.136,
      "p99_ms": 68.654,
      "cv_pct": 3.93,
      "n": 40,
      "all_ms": [
        73.086,
        59.919,
        57.958,
        58.363,
        57.425,
        59.678,
        58.647,
        58.365,
        59.722,
        59.269,
        58.7,
        59.707,
        59.022,
        58.929,
        59.378,
        59.283,
        59.025,
        58.846,
        58.749,
        59.552,
        58.286,
        58.97,
        58.265,
        59.885,
        60.07,
        60.026,
        58.335,
        59.932,
        59.049,
        59.846,
        59.933,
        59.356,
        58.683,
        58.674,
        58.94,
        59.283,
        61.044,
        60.726,
        59.961,
        61.723
      ]
    }
  },
  "inflation": {
    "P": 2.415,
    "D": 2.476
  },
  "gpu": 0,
  "warmup": 15,
  "iterations": 40,
  "action_k": 10,
  "use_cuda": true
}